teeworlds_player_color_value_to_rgb/__init__.py
teeworlds_player_color_value_to_rgb-1.1.0.dist-info/METADATA
teeworlds_player_color_value_to_rgb-1.1.0.dist-info/WHEEL
teeworlds_player_color_value_to_rgb-1.1.0.dist-info/entry_points.txt
teeworlds_player_color_value_to_rgb-1.1.0.dist-info/top_level.txt
teeworlds_player_color_value_to_rgb-1.1.0.dist-info/RECORD
